peer_chat/__init__.py
peer_chat/app.py
peer_chat/config.py
peer_chat/socket.py
peer_chat/wsgi.py
peer_chat/api/__init__.py
peer_chat/api/v0.py
peer_chat/client/asset-manifest.json
peer_chat/client/favicon.ico
peer_chat/client/favicon.png
peer_chat/client/index.html
peer_chat/client/manifest.json
peer_chat/client/peerChat.svg
peer_chat/client/static/css/main.00a999db.css
peer_chat/client/static/js/main.22a89eb5.js
peer_chat/client/static/js/main.22a89eb5.js.LICENSE.txt
peer_chat/common/__init__.py
peer_chat/common/models.py
peer_chat/common/notifier.py
peer_chat/common/store.py
peer_chat/common/update.py
peer_chat/common/util.py
peerchat-0.7.2.dist-info/METADATA
peerchat-0.7.2.dist-info/WHEEL
peerchat-0.7.2.dist-info/entry_points.txt
peerchat-0.7.2.dist-info/top_level.txt
peerchat-0.7.2.dist-info/RECORD
