Metadata-Version: 2.4
Name: peerChat
Version: 0.7.2
Summary: A basic self-hosted peer-to-peer chat application.
Home-page: https://pypi.org/project/peerChat/
Author: Steffen Richters-Finger
Author-email: srichters@uni-muenster.de
License: MIT
Project-URL: Source, https://github.com/RichtersFinger/peerChat
Classifier: Development Status :: 4 - Beta
Classifier: Intended Audience :: End Users/Desktop
Classifier: Topic :: Communications
Classifier: License :: OSI Approved :: MIT License
Classifier: Programming Language :: Python :: 3
Classifier: Programming Language :: Python :: 3.10
Classifier: Programming Language :: Python :: 3.11
Classifier: Programming Language :: Python :: 3.12
Classifier: Framework :: Flask
Requires-Python: >=3.10
Requires-Dist: Flask<4,>=3
Requires-Dist: Flask-SocketIO<6,>=5.4
Requires-Dist: requests<3,>=2.32
Requires-Dist: gunicorn
Requires-Dist: desktop-notifier<7,>=6
Dynamic: author
Dynamic: author-email
Dynamic: classifier
Dynamic: description
Dynamic: description-content-type
Dynamic: home-page
Dynamic: license
Dynamic: project-url
Dynamic: requires-dist
Dynamic: requires-python
Dynamic: summary
